{"connect_count":1,"city":"San Francisco","ip":"76.21.57.0","hostname":"us-east181.discord.gg","timestamp":"2018-07-11T03:59:55.141Z","chosen_locale":"en-US","os_version":"10.0.16299","browser":"Discord Client","domain":"Analytics","client_build_number":18362,"client_send_timestamp":"1531281595016","os":"Windows","user_id":"141734249702096896","detected_locale":"en-US","rtc_connection_id":"f1ca7a14-bba0-4248-865d-84566620d820","country_code":"US","freight_hostname":"api-prd-main-brhs","cfduid":"d73575e295001b74487abdb70cd2570fd1531276066","connect_time":"703","event_source":"client","client_track_timestamp":"1531281594988","release_channel":"stable","event_type":"voice_connection_success","region_code":"CA","client_version":"0.0.301","event_id":"AQMDXlX4D8B53RF1kl2gJIAHoAAAAMU=","day":"896","time_zone":"America/Los_Angeles"}